limma/__init__.py
limma/core.py
limma-0.1.1.dist-info/licenses/LICENSE
limma-0.1.1.dist-info/METADATA
limma-0.1.1.dist-info/WHEEL
limma-0.1.1.dist-info/top_level.txt
limma-0.1.1.dist-info/RECORD
