Metadata-Version: 2.4
Name: limma
Version: 0.1.1
Summary: Language Interface Model for Machine Automation - Control ESP devices with natural language
Home-page: https://github.com/firoziya/limma
Author: Yash Kumar Firoziya
Author-email: ykfiroziya@gmail.com
License: Apache-2.0
Project-URL: Bug Reports, https://github.com/firoziya/limma/issues
Project-URL: Source, https://github.com/firoziya/limma
Project-URL: Documentation, https://limma.live/docs/
Project-URL: Homepage, https://github.com/firoziya/limma
Project-URL: API Key, https://limma.live/
Project-URL: Changelog, https://github.com/firoziya/limma/blob/main/CHANGELOG.md
Keywords: esp8266,esp32,iot,microcontroller,natural-language,automation,home-automation,limma
Platform: any
Classifier: Development Status :: 4 - Beta
Classifier: Intended Audience :: Developers
Classifier: Topic :: Software Development :: Libraries :: Python Modules
Classifier: Topic :: System :: Hardware
Classifier: Topic :: Home Automation
Classifier: Programming Language :: Python :: 3.9
Classifier: Programming Language :: Python :: 3.10
Classifier: Programming Language :: Python :: 3.11
Classifier: Programming Language :: Python :: 3.12
Classifier: Operating System :: OS Independent
Requires-Python: >=3.9
License-File: LICENSE
Requires-Dist: requests>=2.25.0
Provides-Extra: dev
Requires-Dist: pytest>=6.0; extra == "dev"
Requires-Dist: black>=21.0; extra == "dev"
Requires-Dist: flake8>=3.9; extra == "dev"
Requires-Dist: twine>=3.0; extra == "dev"
Provides-Extra: voice
Requires-Dist: pyvoicekit; extra == "voice"
Dynamic: author
Dynamic: author-email
Dynamic: classifier
Dynamic: description
Dynamic: description-content-type
Dynamic: home-page
Dynamic: keywords
Dynamic: license
Dynamic: license-file
Dynamic: platform
Dynamic: project-url
Dynamic: provides-extra
Dynamic: requires-dist
Dynamic: requires-python
Dynamic: summary
